genClaude/__init__.py
genClaude/get_response.py
genClaude-0.0.1.dist-info/METADATA
genClaude-0.0.1.dist-info/WHEEL
genClaude-0.0.1.dist-info/top_level.txt
genClaude-0.0.1.dist-info/RECORD
